sortedcontainers_pydantic/__init__.py
sortedcontainers_pydantic/py.typed
sortedcontainers_pydantic-2.0.0.dist-info/METADATA
sortedcontainers_pydantic-2.0.0.dist-info/WHEEL
sortedcontainers_pydantic-2.0.0.dist-info/licenses/LICENSE
sortedcontainers_pydantic-2.0.0.dist-info/RECORD
