Metadata-Version: 2.4
Name: sortedcontainers-pydantic
Version: 2.0.0
Summary: Pydantic support for the sortedcontainers package.
Project-URL: Homepage, https://github.com/jayqi/sortedcontainers-pydantic/
Project-URL: Repository, https://github.com/jayqi/sortedcontainers-pydantic
Project-URL: Bug Tracker, https://github.com/jayqi/sortedcontainers-pydantic/issues
Author-email: DrivenData <info@drivendata.org>, Jay Qi <jayqi.opensource@gmail.com>
License: MIT License
License-File: LICENSE
Keywords: pydantic,sorted,sorteddict,sortedlist,sortedset
Classifier: Framework :: Pydantic
Classifier: Framework :: Pydantic :: 2
Classifier: Intended Audience :: Developers
Classifier: License :: OSI Approved :: MIT License
Classifier: Operating System :: OS Independent
Classifier: Programming Language :: Python :: 3
Classifier: Programming Language :: Python :: 3.9
Classifier: Programming Language :: Python :: 3.10
Classifier: Programming Language :: Python :: 3.11
Classifier: Programming Language :: Python :: 3.12
Classifier: Programming Language :: Python :: 3.13
Requires-Python: >=3.9
Requires-Dist: pydantic-core
Requires-Dist: pydantic>=2
Requires-Dist: sortedcontainers
Provides-Extra: tests
Requires-Dist: pytest>=6; extra == 'tests'
